MANIFEST.in
README.md
__init__.py
setup.py
bin/__init__.py
bin/qasino_csvpublisher.py
bin/qasino_publish.py
bin/qasino_sqlclient.py
bin/qasinobatchpub
bin/qasinocsvpub
bin/qasinosql
lib/__init__.py
lib/apsw_connection.py
lib/constants.py
lib/csv_table_reader.py
lib/data_manager.py
lib/http_receiver.py
lib/http_receiver_ui.py
lib/http_requestor.py
lib/qasino_table.py
lib/sql_receiver.py
lib/sqlite_backend.py
lib/table_merger.py
lib/util.py
lib/zmq_publisher.py
lib/zmq_receiver.py
lib/zmq_requestor.py
lib/zmq_subscriber.py
qasino_client.egg-info/PKG-INFO
qasino_client.egg-info/SOURCES.txt
qasino_client.egg-info/dependency_links.txt
qasino_client.egg-info/requires.txt
qasino_client.egg-info/top_level.txt