Metadata-Version: 1.1
Name: qasino-client
Version: 1.6.2
Summary: A command line client for the qasino project.
Home-page: https://github.com/MediaMath/qasino
Author: UNKNOWN
Author-email: UNKNOWN
License: Apache 2.0
Keywords: qasino stats monitoring mediamath
Platform: UNKNOWN
Classifier: License :: OSI Approved :: Apache Software License
Classifier: Development Status :: 5 - Production/Stable
Classifier: Intended Audience :: Developers
Classifier: Topic :: System :: Monitoring
Classifier: Programming Language :: Python :: 2.7
